llm_anon/__init__.py
llm_anon/anonymizer.py
llm_anon/cli.py
llm_anon/file_processor.py
llm_anon/types.py
llm_anon/validator.py
llm_anon-0.1.1.dist-info/licenses/LICENSE
llm_anon-0.1.1.dist-info/METADATA
llm_anon-0.1.1.dist-info/WHEEL
llm_anon-0.1.1.dist-info/entry_points.txt
llm_anon-0.1.1.dist-info/top_level.txt
llm_anon-0.1.1.dist-info/RECORD
