Metadata-Version: 2.4
Name: llm-anon
Version: 0.1.1
Summary: CLI tool to anonymize code using local LLM before sending to Claude Code
Author-email: Christian Bakopoulos <christian.bakopoulos@gmail.com>
License-Expression: MIT
Project-URL: Homepage, https://github.com/ChristianBako/LLM-Anonymizer-
Project-URL: Repository, https://github.com/ChristianBako/LLM-Anonymizer-.git
Project-URL: Issues, https://github.com/ChristianBako/LLM-Anonymizer-/issues
Keywords: anonymization,llm,code,privacy,claude,ollama
Classifier: Development Status :: 4 - Beta
Classifier: Intended Audience :: Developers
Classifier: Operating System :: MacOS
Classifier: Programming Language :: Python :: 3
Classifier: Programming Language :: Python :: 3.9
Classifier: Programming Language :: Python :: 3.10
Classifier: Programming Language :: Python :: 3.11
Classifier: Programming Language :: Python :: 3.12
Classifier: Topic :: Software Development :: Libraries :: Python Modules
Classifier: Topic :: Security
Classifier: Topic :: Text Processing
Requires-Python: >=3.9
License-File: LICENSE
Requires-Dist: click>=8.0.0
Requires-Dist: ollama>=0.3.0
Requires-Dist: typing-extensions>=4.0.0
Dynamic: license-file
